{
  "issue_number": 1152,
  "issue_title": "\ud83c\udfaf Mission: Web: Api Innovation",
  "issue_labels": [
    "automated",
    "learning",
    "ai-generated",
    "agent-mission",
    "location-us-san francisco",
    "pattern-api",
    "pattern-web"
  ],
  "total_comments": 0,
  "participants": [
    "github-actions[bot]"
  ],
  "duration_hours": 0.0,
  "insights": [
    {
      "issue_number": 1152,
      "issue_title": "\ud83c\udfaf Mission: Web: Api Innovation",
      "insight_type": "agent_behavior",
      "content": "## \ud83c\udfaf Agent Mission: Web: Api Innovation\n\n**Mission ID:** idea:19\n**Created:** 2025-11-16 02:37:51 UTC\n\n### \ud83d\udccb Mission Summary\n\nExploring api trends with 16 mentions",
      "context": "## \ud83c\udfaf Agent Mission: Web: Api Innovation\n\n**Mission ID:** idea:19\n**Created:** 2025-11-16 02:37:51 UTC\n\n### \ud83d\udccb Mission Summary\n\nExploring api trends with 16 mentions. requestly/requestly - Free and open",
      "participants": [
        "issue_author"
      ],
      "timestamp": "2025-11-16T02:37:52Z",
      "confidence": 0.7,
      "tags": [
        "api",
        "agent"
      ]
    },
    {
      "issue_number": 1152,
      "issue_title": "\ud83c\udfaf Mission: Web: Api Innovation",
      "insight_type": "agent_behavior",
      "content": "### \ud83c\udf0d Mission Locations\n\nUS:San Francisco\n\n### \ud83c\udff7\ufe0f Patterns & Technologies\n\napi, web\n\n### \ud83e\udd16 Assigned Agent\n\n**Unknown** (@unknown) - Match Score: 0",
      "context": "## \ud83c\udfaf Agent Mission: Web: Api Innovation\n\n**Mission ID:** idea:19\n**Created:** 2025-11-16 02:37:51 UTC\n\n### \ud83d\udccb Mission Summary\n\nExploring api trends with 16 mentions. requestly/requestly - Free and open",
      "participants": [
        "issue_author"
      ],
      "timestamp": "2025-11-16T02:37:52Z",
      "confidence": 0.7,
      "tags": [
        "api",
        "agent"
      ]
    },
    {
      "issue_number": 1152,
      "issue_title": "\ud83c\udfaf Mission: Web: Api Innovation",
      "insight_type": "technical",
      "content": "00\n\nThis mission was matched to **@unknown** based on:\n- Location relevance (30%)\n- Role/skill match (40%)  \n- Performance history (30%)\n\n### \ud83d\udcca Expected Outputs\n\n- [ ] Documentation related to api, web\n- [ ] Code examples or tools\n- [ ] World model updates\n- [ ] Learning artifacts\n\n### \ud83d\udd04 Next Steps\n\n1",
      "context": "## \ud83c\udfaf Agent Mission: Web: Api Innovation\n\n**Mission ID:** idea:19\n**Created:** 2025-11-16 02:37:51 UTC\n\n### \ud83d\udccb Mission Summary\n\nExploring api trends with 16 mentions. requestly/requestly - Free and open",
      "participants": [
        "issue_author"
      ],
      "timestamp": "2025-11-16T02:37:52Z",
      "confidence": 0.7999999999999999,
      "tags": [
        "api",
        "learning"
      ]
    },
    {
      "issue_number": 1152,
      "issue_title": "\ud83c\udfaf Mission: Web: Api Innovation",
      "insight_type": "process",
      "content": "Agent metrics are updated based on contributions\n\n---\n\n*This mission was automatically created by the Agent Missions workflow and assigned to **@unknown** based on intelligent matching",
      "context": "## \ud83c\udfaf Agent Mission: Web: Api Innovation\n\n**Mission ID:** idea:19\n**Created:** 2025-11-16 02:37:51 UTC\n\n### \ud83d\udccb Mission Summary\n\nExploring api trends with 16 mentions. requestly/requestly - Free and open",
      "participants": [
        "issue_author"
      ],
      "timestamp": "2025-11-16T02:37:52Z",
      "confidence": 0.7,
      "tags": [
        "workflow",
        "agent"
      ]
    }
  ],
  "key_decisions": [],
  "patterns_identified": [],
  "learning_quality": 0.145,
  "timestamp": "2025-11-16T02:43:35.970067+00:00"
}